web_tool/__init__.py
web_tool/server.py
web_tool_mcp_server-0.0.2.dist-info/METADATA
web_tool_mcp_server-0.0.2.dist-info/WHEEL
web_tool_mcp_server-0.0.2.dist-info/entry_points.txt
web_tool_mcp_server-0.0.2.dist-info/top_level.txt
web_tool_mcp_server-0.0.2.dist-info/RECORD
