Metadata-Version: 2.4
Name: web-tool-mcp-server
Version: 0.0.2
Summary: linview's MCP server tools for web utilities
Home-page: https://github.com/linview/sandbox_agent
Author: linview
Author-email: linview <linview@gmail.com>
License: MIT
Project-URL: Homepage, https://github.com/linview/sandbox_agent
Project-URL: Repository, https://github.com/linview/sandbox_agent
Classifier: Development Status :: 4 - Beta
Classifier: Intended Audience :: Developers
Classifier: License :: OSI Approved :: MIT License
Classifier: Programming Language :: Python :: 3.10
Classifier: Programming Language :: Python :: 3.11
Requires-Python: >=3.10
Requires-Dist: fastmcp>=1.0.0
Requires-Dist: pydantic>=2.0.0
Requires-Dist: requests>=2.28.0
Requires-Dist: beautifulsoup4>=4.11.0
Dynamic: author
Dynamic: home-page
Dynamic: requires-python
